AUTHORS
LICENSE
MANIFEST.in
README.rst
setup.py
competition/__init__.py
competition/admin.py
competition/generator.py
competition/models.py
competition/tests.py
competition/urls.py
competition/view_modifiers.py
competition/views.py
competition/fixtures/photosizes.json
competition/templates/competition/competition_detail.html
competition/templates/competition/competition_list.html
competition/templates/competition/competitionpreferences_detail.html
competition/templates/competition/inclusion_tags/competition_detail.html
competition/templates/competition/inclusion_tags/competition_list_wide.html
competition/templates/competition/inclusion_tags/competition_listing.html
competition/templatetags/__init__.py
competition/templatetags/competition_inclusion_tags.py
panya_competition.egg-info/PKG-INFO
panya_competition.egg-info/SOURCES.txt
panya_competition.egg-info/dependency_links.txt
panya_competition.egg-info/not-zip-safe
panya_competition.egg-info/requires.txt
panya_competition.egg-info/top_level.txt