Metadata-Version: 1.0
Name: panya-competition
Version: 0.0.4
Summary: Panya competition app.
Home-page: http://github.com/praekelt/panya-competition
Author: Praekelt International
Author-email: dev@praekelt.com
License: BSD
Platform: UNKNOWN
Classifier: Programming Language :: Python
Classifier: License :: OSI Approved :: BSD License
Classifier: Development Status :: 4 - Beta
Classifier: Operating System :: OS Independent
Classifier: Framework :: Django
Classifier: Intended Audience :: Developers
Classifier: Topic :: Internet :: WWW/HTTP :: Dynamic Content
